{
  "fajr": {
    "title": "ফজরের নামাজ",
    "rakat": "২ রাকাত সুন্নাত + ২ রাকাত ফরজ",
    "time": "ভোর থেকে সূর্যোদয়ের আগে পর্যন্ত",
    "fazilat": "রাসূল ﷺ বলেছেন, “যে ফজরের নামাজ আদায় করল, সে আল্লাহর জিম্মায় রইল।”",
    "details": {
      "sunnah": [
        "নিয়ত: নাওয়াইতু আন উসাল্লি লিল্লাহি তা'আলা রাকআতাই সুন্নাতি সালাতিল ফজর",
        "তাকবিরে তাহরিমা: اللهُ أَكْبَرُ (আল্লাহু আকবার)",
        "সানা: سُبْحَانَكَ اللَّهُمَّ وَبِحَمْدِكَ...",
        "সূরা ফাতিহা ও অন্য সূরা (যেমন সূরা ইখলাস)",
        "রুকু: سُبْحَانَ رَبِّيَ الْعَظِيمِ",
        "সিজদাহ: سُبْحَانَ رَبِّيَ الْأَعْلَى",
        "শেষ বৈঠকে: তাশাহহুদ, দরুদ, দোয়া, সালাম"
      ],
      "farz": [
        "একই নিয়মে পড়ুন, কিরাত নিঃশব্দে পড়তে হবে।"
      ]
    }
  },
  "dhuhr": {
    "title": "যোহরের নামাজ",
    "rakat": "৪ রাকাত সুন্নাত + ৪ রাকাত ফরজ + ২ রাকাত সুন্নাত",
    "time": "সূর্য হেলে পড়া থেকে প্রতিটি বস্তুর ছায়া সমান হওয়া পর্যন্ত",
    "details": {
      "sunnah_before": [
        "ফজরের সুন্নাতের মতোই পড়ুন, তবে ৪ রাকাত।"
      ],
      "farz": [
        "নিয়ত করুন: নাওয়াইতু আন উসাল্লি লিল্লাহি তা’আলা রাকআরবা সালাতাদ-যোহর ফরজান...",
        "প্রথম দুই রাকাত: সূরা ফাতিহা ও অন্য সূরা নিঃশব্দে।",
        "শেষ দুই রাকাত: শুধু সূরা ফাতিহা নিঃশব্দে।",
        "শেষ বৈঠকে: তাশাহহুদ, দরুদ ও দোয়া পড়ুন।"
      ],
      "sunnah_after": [
        "ফজরের সুন্নাতের মতোই ২ রাকাত পড়ুন।"
      ]
    }
  },
  "asr": {
    "title": "আসরের নামাজ",
    "rakat": "৪ রাকাত ফরজ",
    "time": "যোহরের সময় শেষ হওয়ার পর থেকে সূর্যাস্ত পর্যন্ত",
    "fazilat": "রাসূল ﷺ বলেছেন, “যে আসরের নামাজ আদায় করল, তার জন্য জান্নাত ওয়াজিব।”",
    "details": {
      "farz": [
        "যোহরের ফরজের মতোই পড়ুন, সব কিরাত নিঃশব্দে।"
      ]
    }
  },
  "maghrib": {
    "title": "মাগরিবের নামাজ",
    "rakat": "৩ রাকাত ফরজ + ২ রাকাত সুন্নাত",
    "time": "সূর্যাস্তের পর থেকে আকাশের লাল আভা মিলিয়ে যাওয়া পর্যন্ত",
    "details": {
      "farz": [
        "প্রথম দুই রাকাত: সূরা ফাতিহা ও অন্য সূরা সশব্দে।",
        "তৃতীয় রাকাত: শুধু সূরা ফাতিহা নিঃশব্দে।",
        "শেষ বৈঠকে: তাশাহহুদ, দরুদ ও দোয়া পড়ুন।"
      ],
      "sunnah": [
        "ফজরের সুন্নাতের মতোই ২ রাকাত পড়ুন।"
      ]
    }
  },
  "isha": {
    "title": "এশার নামাজ",
    "rakat": "৪ রাকাত ফরজ + ২ রাকাত সুন্নাত + ৩ রাকাত বিতর",
    "time": "মাগরিবের সময় শেষ হওয়ার পর থেকে ফজরের ওয়াক্ত শুরু হওয়া পর্যন্ত",
    "details": {
      "farz": [
        "যোহরের ফরজের মতোই পড়ুন, তবে প্রথম দুই রাকাত সশব্দে।"
      ],
      "sunnah": [
        "ফজরের সুন্নাতের মতোই ২ রাকাত পড়ুন।"
      ],
      "witr": [
        "প্রথম দুই রাকাত: সাধারণ নামাজের মতো পড়ুন।",
        "তৃতীয় রাকাত: সূরা ফাতিহার পর দোয়া কুনুত পড়ুন।",
        "শেষ বৈঠকে: তাশাহহুদ, দরুদ, দোয়া ও সালাম।"
      ]
    }
  },
  "eid": {
    "title": "ঈদের নামাজ",
    "rakat": "২ রাকাত (ফরজ নয়, ওয়াজিব বা সুন্নাত মুয়াক্কাদাহ)",
    "time": "সূর্য উদয় হয়ে উঁচু হওয়ার পর থেকে যোহরের আগে পর্যন্ত",
    "details": {
      "steps": [
        "নিয়ত করুন: নাওয়াইতু আন উসাল্লি লিল্লাহি তা’আলা রাক‘আতাই সালাতিল ঈদ...",
        "প্রথম রাকাতে তাকবিরে তাহরিমার পর সানা, তারপর অতিরিক্ত ৩ তাকবির দিন।",
        "সূরা ফাতিহা ও অন্য সূরা (যেমন সূরা আল-আলা) পড়ুন।",
        "রুকু, সিজদাহ করুন এবং দ্বিতীয় রাকাতে কিরাতের আগে আবার ৩ তাকবির দিন।",
        "দ্বিতীয় রাকাত শেষে তাশাহহুদ, দরুদ ও দোয়া পড়ে সালাম ফিরান।",
        "নামাজের পর খুতবা শোনা সুন্নাত।"
      ]
    }
  },
  "janaza": {
    "title": "জানাজার নামাজ",
    "rakat": "রাকাত নেই – এটি কেবল তাকবির ও দোয়ার সমষ্টি",
    "time": "যেকোনো সময়, তবে মাকরুহ সময় ব্যতীত",
    "details": {
      "steps": [
        "নিয়ত করুন: নাওয়াইতু আন উসাল্লি লিল্লাহি তা’আলা সালাতাল জানাযা...",
        "১ম তাকবির: তাকবিরের পর সানা পড়ুন।",
        "২য় তাকবির: দরুদ শরীফ পড়ুন।",
        "৩য় তাকবির: মৃতের জন্য দোয়া করুন (যেমন: আল্লাহুম্মাগফির লিহাইয়িনা ওয়া মাইয়িতিনা…).",
        "৪র্থ তাকবির: অল্প বিরতি নিয়ে ডানে-বামে সালাম ফিরান।"
      ]
    }
  }
}
